bruin/__init__.py
bruin/__main__.py
bruin/calendar_tool.py
bruin/meal.py
bruin/tasks.py
bruin/secret/client_secret.json
bruin-0.3.3.dist-info/LICENSE
bruin-0.3.3.dist-info/METADATA
bruin-0.3.3.dist-info/WHEEL
bruin-0.3.3.dist-info/dependency_links.txt
bruin-0.3.3.dist-info/entry_points.txt
bruin-0.3.3.dist-info/top_level.txt
bruin-0.3.3.dist-info/RECORD
