Metadata-Version: 2.1
Name: bruin
Version: 0.3.3
Summary: Command line tool made by python for various toolbox used in UCLA
Home-page: https://github.com/OswaldHe/bruin-cli
Author: Oswald He
License: MIT
Platform: UNKNOWN
Requires-Python: >=3.6
Requires-Dist: beautifulsoup4 (==4.9.3)
Requires-Dist: bleach (==4.1.0)
Requires-Dist: cachetools (==4.2.2)
Requires-Dist: certifi (==2021.5.30)
Requires-Dist: charset-normalizer (==2.0.4)
Requires-Dist: colorama (==0.4.4)
Requires-Dist: docutils (==0.17.1)
Requires-Dist: google-api-core (==2.0.1)
Requires-Dist: google-api-python-client (==2.19.1)
Requires-Dist: google-auth (==2.0.2)
Requires-Dist: google-auth-httplib2 (==0.1.0)
Requires-Dist: google-auth-oauthlib (==0.4.6)
Requires-Dist: googleapis-common-protos (==1.53.0)
Requires-Dist: httplib2 (==0.19.1)
Requires-Dist: idna (==3.2)
Requires-Dist: importlib-metadata (==4.8.1)
Requires-Dist: iso8601 (==0.1.16)
Requires-Dist: keyring (==23.1.0)
Requires-Dist: lxml (==4.6.3)
Requires-Dist: oauthlib (==3.1.1)
Requires-Dist: packaging (==21.0)
Requires-Dist: pathlib (==1.0.1)
Requires-Dist: pkginfo (==1.7.1)
Requires-Dist: protobuf (==3.17.3)
Requires-Dist: pyasn1 (==0.4.8)
Requires-Dist: pyasn1-modules (==0.2.8)
Requires-Dist: Pygments (==2.10.0)
Requires-Dist: pyparsing (==2.4.7)
Requires-Dist: readme-renderer (==29.0)
Requires-Dist: requests (==2.26.0)
Requires-Dist: requests-oauthlib (==1.3.0)
Requires-Dist: requests-toolbelt (==0.9.1)
Requires-Dist: rfc3986 (==1.5.0)
Requires-Dist: rsa (==4.7.2)
Requires-Dist: six (==1.16.0)
Requires-Dist: soupsieve (==2.2.1)
Requires-Dist: termcolor (==1.1.0)
Requires-Dist: tqdm (==4.62.2)
Requires-Dist: twine (==3.4.2)
Requires-Dist: typing-extensions (==3.10.0.2)
Requires-Dist: Unidecode (==1.2.0)
Requires-Dist: uritemplate (==3.0.1)
Requires-Dist: urllib3 (==1.26.6)
Requires-Dist: webencodings (==0.5.1)
Requires-Dist: zipp (==3.5.0)
